jbridgedf/__init__.py
jbridgedf/parser.py
jbridgedf-0.1.5.dist-info/licenses/LICENSE
jbridgedf-0.1.5.dist-info/METADATA
jbridgedf-0.1.5.dist-info/WHEEL
jbridgedf-0.1.5.dist-info/top_level.txt
jbridgedf-0.1.5.dist-info/RECORD
