Metadata-Version: 2.4
Name: jbridgedf
Version: 0.1.5
Summary: A robust Python library to parse API JSON responses into DataFrames with date handling.
Author: Luis Felipe de Moraes
Author-email: Luis Felipe De Moraes <luismoraes.datascience@gmail.com>
License: MIT
Classifier: Programming Language :: Python :: 3
Classifier: License :: OSI Approved :: MIT License
Classifier: Operating System :: OS Independent
Classifier: Topic :: Software Development :: Libraries
Classifier: Intended Audience :: Developers
Requires-Python: >=3.8
License-File: LICENSE
Requires-Dist: pandas
Requires-Dist: requests
Dynamic: author
Dynamic: license-file
Dynamic: requires-python
